satellitecenter/__init__.py
satellitecenter/_version.py
satellitecenter/main.py
satellitecenter/config/__init__.py
satellitecenter/config/indicator_mapping.py
satellitecenter/utils/__init__.py
satellitecenter/utils/config_loader.py
satellitecenter/utils/encryption.py
satellitecenter/utils/indicator_standardizer.py
satellitecenter-1.1.1.dist-info/METADATA
satellitecenter-1.1.1.dist-info/WHEEL
satellitecenter-1.1.1.dist-info/entry_points.txt
satellitecenter-1.1.1.dist-info/top_level.txt
satellitecenter-1.1.1.dist-info/RECORD
