Metadata-Version: 2.4
Name: satellitecenter
Version: 1.1.1
Summary: 卫星中心自动化建模工具 - 用于处理遥感数据的光谱与实测数据匹配和建模
Author-email: Your Name <your.email@example.com>
License: MIT
Project-URL: Homepage, https://github.com/1034378361/SateliteCenter
Project-URL: Documentation, https://github.com/1034378361/SateliteCenter/wiki
Project-URL: Repository, https://github.com/1034378361/SateliteCenter.git
Project-URL: Issues, https://github.com/1034378361/SateliteCenter/issues
Keywords: satellite,hyperspectral,water-quality,modeling
Classifier: Development Status :: 3 - Alpha
Classifier: Intended Audience :: Science/Research
Classifier: Programming Language :: Python :: 3
Classifier: Programming Language :: Python :: 3.12
Classifier: Topic :: Scientific/Engineering
Requires-Python: >=3.12
Requires-Dist: numpy>=2.3.4
Requires-Dist: pandas>=2.3.3
Provides-Extra: dev
Requires-Dist: pytest>=7.4.0; extra == "dev"
Requires-Dist: pytest-cov>=4.1.0; extra == "dev"
Requires-Dist: black>=23.12.0; extra == "dev"
Requires-Dist: ruff>=0.1.9; extra == "dev"
Requires-Dist: mypy>=1.8.0; extra == "dev"
Requires-Dist: isort>=5.13.0; extra == "dev"
Requires-Dist: bandit>=1.7.5; extra == "dev"
Requires-Dist: pip-audit>=2.6.1; extra == "dev"
Requires-Dist: setuptools_scm[toml]>=6.2; extra == "dev"
